LICENSE.md
README.md
pyproject.toml
setup.cfg
setup.py
etc/firecli-complete.sh
etc/firecli.yml
etc/logging.yml
etc/overrides.yml
firecli/__init__.py
firecli/__main__.py
firecli/version.py
firecli.egg-info/PKG-INFO
firecli.egg-info/SOURCES.txt
firecli.egg-info/dependency_links.txt
firecli.egg-info/entry_points.txt
firecli.egg-info/requires.txt
firecli.egg-info/top_level.txt
firecli/api/__init__.py
firecli/api/afa/__init__.py
firecli/api/cache/__init__.py
firecli/api/cfg/__init__.py
firecli/api/click/__init__.py
firecli/api/click/callback.py
firecli/api/compliance/__init__.py
firecli/api/helper/__init__.py
firecli/api/report/__init__.py
firecli/api/state/__init__.py
firecli/cli/__init__.py
firecli/cli/helper.py
firecli/cli/accesspolicy/__init__.py
firecli/cli/accesspolicy/filepolicy/__init__.py
firecli/cli/cache/__init__.py
firecli/cli/compliance/__init__.py
firecli/cli/log/__init__.py
firecli/cli/object/__init__.py
firecli/cli/object/dnsservergroup/__init__.py
firecli/cli/object/dnsservergroup/override/__init__.py
firecli/cli/object/host/__init__.py
firecli/cli/object/host/override/__init__.py
firecli/cli/object/ipv4addresspool/__init__.py
firecli/cli/object/ipv4addresspool/override/__init__.py
firecli/cli/object/network/__init__.py
firecli/cli/object/network/override/__init__.py
firecli/cli/object/networkgroup/__init__.py
firecli/cli/object/networkgroup/override/__init__.py
firecli/cli/object/override/__init__.py
firecli/cli/object/range/__init__.py
firecli/cli/object/range/override/__init__.py
firecli/cli/object/timezone/__init__.py
firecli/cli/object/timezone/override/__init__.py
firecli/cli/object/url/__init__.py
firecli/cli/object/url/override/__init__.py
firecli/cli/report/__init__.py
firecli/cli/s2svpn/__init__.py
firecli/cli/s2svpn/point2point/__init__.py
firecli/cli/sync/__init__.py
test/__init__.py
test/conftest.py
test/api/__init__.py
test/api/cfg/__init__.py
test/api/cfg/test_cfg.py
test/cli/__init__.py
test/cli/test_cli.py
test/cli/test_log.py
test/cli/test_report.py