Metadata-Version: 2.1
Name: firecli
Version: 1.1.3
Summary: FireCLI is a command line interface to Firepower Management Center
Home-page: https://git.ong.at/cisco/firecli.git
Author: Oliver Kaiser
Author-email: oliver.kaiser@outlook.com
Keywords: cisco firepower fmc ftd fpr api rest python api cli
Classifier: Intended Audience :: Developers
Classifier: Intended Audience :: Information Technology
Classifier: License :: OSI Approved :: MIT License
Classifier: Natural Language :: English
Classifier: Operating System :: POSIX
Classifier: Programming Language :: Python :: 3
License-File: LICENSE.md
